[
  {
    "name": "Application Start",
    "start": 1576571542273,
    "end": 1576571542618,
    "duration": 345,
    "pid": 57457,
    "index": 0
  },
  {
    "name": "Load Plugin",
    "start": 1576571542276,
    "end": 1576571542282,
    "duration": 6,
    "pid": 57457,
    "index": 1
  },
  {
    "name": "Load Config",
    "start": 1576571542282,
    "end": 1576571542292,
    "duration": 10,
    "pid": 57457,
    "index": 2
  },
  {
    "name": "Require(0) config/config.default.js",
    "start": 1576571542282,
    "end": 1576571542282,
    "duration": 0,
    "pid": 57457,
    "index": 3
  },
  {
    "name": "Require(1) node_modules/egg-session/config/config.default.js",
    "start": 1576571542283,
    "end": 1576571542284,
    "duration": 1,
    "pid": 57457,
    "index": 4
  },
  {
    "name": "Require(2) node_modules/egg-security/config/config.default.js",
    "start": 1576571542284,
    "end": 1576571542284,
    "duration": 0,
    "pid": 57457,
    "index": 5
  },
  {
    "name": "Require(3) node_modules/egg-jsonp/config/config.default.js",
    "start": 1576571542284,
    "end": 1576571542285,
    "duration": 1,
    "pid": 57457,
    "index": 6
  },
  {
    "name": "Require(4) node_modules/egg-onerror/config/config.default.js",
    "start": 1576571542285,
    "end": 1576571542285,
    "duration": 0,
    "pid": 57457,
    "index": 7
  },
  {
    "name": "Require(5) node_modules/egg-i18n/config/config.default.js",
    "start": 1576571542285,
    "end": 1576571542285,
    "duration": 0,
    "pid": 57457,
    "index": 8
  },
  {
    "name": "Require(6) node_modules/egg-watcher/config/config.default.js",
    "start": 1576571542285,
    "end": 1576571542285,
    "duration": 0,
    "pid": 57457,
    "index": 9
  },
  {
    "name": "Require(7) node_modules/egg-schedule/config/config.default.js",
    "start": 1576571542286,
    "end": 1576571542286,
    "duration": 0,
    "pid": 57457,
    "index": 10
  },
  {
    "name": "Require(8) node_modules/egg-multipart/config/config.default.js",
    "start": 1576571542286,
    "end": 1576571542286,
    "duration": 0,
    "pid": 57457,
    "index": 11
  },
  {
    "name": "Require(9) node_modules/egg-development/config/config.default.js",
    "start": 1576571542286,
    "end": 1576571542287,
    "duration": 1,
    "pid": 57457,
    "index": 12
  },
  {
    "name": "Require(10) node_modules/egg-logrotator/config/config.default.js",
    "start": 1576571542287,
    "end": 1576571542287,
    "duration": 0,
    "pid": 57457,
    "index": 13
  },
  {
    "name": "Require(11) node_modules/egg-static/config/config.default.js",
    "start": 1576571542287,
    "end": 1576571542287,
    "duration": 0,
    "pid": 57457,
    "index": 14
  },
  {
    "name": "Require(12) node_modules/egg-view/config/config.default.js",
    "start": 1576571542288,
    "end": 1576571542288,
    "duration": 0,
    "pid": 57457,
    "index": 15
  },
  {
    "name": "Require(13) node_modules/egg-cors/config/config.default.js",
    "start": 1576571542288,
    "end": 1576571542288,
    "duration": 0,
    "pid": 57457,
    "index": 16
  },
  {
    "name": "Require(14) node_modules/egg-mysql/config/config.default.js",
    "start": 1576571542288,
    "end": 1576571542288,
    "duration": 0,
    "pid": 57457,
    "index": 17
  },
  {
    "name": "Require(15) node_modules/egg-socket.io/config/config.default.js",
    "start": 1576571542289,
    "end": 1576571542289,
    "duration": 0,
    "pid": 57457,
    "index": 18
  },
  {
    "name": "Require(16) node_modules/egg/config/config.default.js",
    "start": 1576571542289,
    "end": 1576571542289,
    "duration": 0,
    "pid": 57457,
    "index": 19
  },
  {
    "name": "Require(17) config/config.default.js",
    "start": 1576571542290,
    "end": 1576571542290,
    "duration": 0,
    "pid": 57457,
    "index": 20
  },
  {
    "name": "Require(18) node_modules/egg-security/config/config.local.js",
    "start": 1576571542291,
    "end": 1576571542291,
    "duration": 0,
    "pid": 57457,
    "index": 21
  },
  {
    "name": "Require(19) node_modules/egg-watcher/config/config.local.js",
    "start": 1576571542291,
    "end": 1576571542291,
    "duration": 0,
    "pid": 57457,
    "index": 22
  },
  {
    "name": "Require(20) node_modules/egg-view/config/config.local.js",
    "start": 1576571542291,
    "end": 1576571542292,
    "duration": 1,
    "pid": 57457,
    "index": 23
  },
  {
    "name": "Require(21) node_modules/egg/config/config.local.js",
    "start": 1576571542292,
    "end": 1576571542292,
    "duration": 0,
    "pid": 57457,
    "index": 24
  },
  {
    "name": "Load extend/application.js",
    "start": 1576571542293,
    "end": 1576571542311,
    "duration": 18,
    "pid": 57457,
    "index": 25
  },
  {
    "name": "Require(22) node_modules/egg-session/app/extend/application.js",
    "start": 1576571542293,
    "end": 1576571542293,
    "duration": 0,
    "pid": 57457,
    "index": 26
  },
  {
    "name": "Require(23) node_modules/egg-security/app/extend/application.js",
    "start": 1576571542293,
    "end": 1576571542294,
    "duration": 1,
    "pid": 57457,
    "index": 27
  },
  {
    "name": "Require(24) node_modules/egg-jsonp/app/extend/application.js",
    "start": 1576571542294,
    "end": 1576571542294,
    "duration": 0,
    "pid": 57457,
    "index": 28
  },
  {
    "name": "Require(25) node_modules/egg-logrotator/app/extend/application.js",
    "start": 1576571542295,
    "end": 1576571542295,
    "duration": 0,
    "pid": 57457,
    "index": 29
  },
  {
    "name": "Require(26) node_modules/egg-view/app/extend/application.js",
    "start": 1576571542295,
    "end": 1576571542296,
    "duration": 1,
    "pid": 57457,
    "index": 30
  },
  {
    "name": "Require(27) node_modules/egg-socket.io/app/extend/application.js",
    "start": 1576571542296,
    "end": 1576571542310,
    "duration": 14,
    "pid": 57457,
    "index": 31
  },
  {
    "name": "Load extend/request.js",
    "start": 1576571542311,
    "end": 1576571542313,
    "duration": 2,
    "pid": 57457,
    "index": 32
  },
  {
    "name": "Require(28) node_modules/egg/app/extend/request.js",
    "start": 1576571542311,
    "end": 1576571542312,
    "duration": 1,
    "pid": 57457,
    "index": 33
  },
  {
    "name": "Load extend/response.js",
    "start": 1576571542313,
    "end": 1576571542316,
    "duration": 3,
    "pid": 57457,
    "index": 34
  },
  {
    "name": "Require(29) node_modules/egg/app/extend/response.js",
    "start": 1576571542313,
    "end": 1576571542314,
    "duration": 1,
    "pid": 57457,
    "index": 35
  },
  {
    "name": "Load extend/context.js",
    "start": 1576571542316,
    "end": 1576571542354,
    "duration": 38,
    "pid": 57457,
    "index": 36
  },
  {
    "name": "Require(30) node_modules/egg-security/app/extend/context.js",
    "start": 1576571542317,
    "end": 1576571542320,
    "duration": 3,
    "pid": 57457,
    "index": 37
  },
  {
    "name": "Require(31) node_modules/egg-jsonp/app/extend/context.js",
    "start": 1576571542321,
    "end": 1576571542321,
    "duration": 0,
    "pid": 57457,
    "index": 38
  },
  {
    "name": "Require(32) node_modules/egg-i18n/app/extend/context.js",
    "start": 1576571542321,
    "end": 1576571542321,
    "duration": 0,
    "pid": 57457,
    "index": 39
  },
  {
    "name": "Require(33) node_modules/egg-multipart/app/extend/context.js",
    "start": 1576571542321,
    "end": 1576571542352,
    "duration": 31,
    "pid": 57457,
    "index": 40
  },
  {
    "name": "Require(34) node_modules/egg-view/app/extend/context.js",
    "start": 1576571542352,
    "end": 1576571542352,
    "duration": 0,
    "pid": 57457,
    "index": 41
  },
  {
    "name": "Require(35) lib/plugin/egg-ua/app/extend/context.js",
    "start": 1576571542353,
    "end": 1576571542353,
    "duration": 0,
    "pid": 57457,
    "index": 42
  },
  {
    "name": "Require(36) node_modules/egg/app/extend/context.js",
    "start": 1576571542353,
    "end": 1576571542353,
    "duration": 0,
    "pid": 57457,
    "index": 43
  },
  {
    "name": "Require(37) app/extend/context.js",
    "start": 1576571542354,
    "end": 1576571542354,
    "duration": 0,
    "pid": 57457,
    "index": 44
  },
  {
    "name": "Load extend/helper.js",
    "start": 1576571542354,
    "end": 1576571542363,
    "duration": 9,
    "pid": 57457,
    "index": 45
  },
  {
    "name": "Require(38) node_modules/egg-security/app/extend/helper.js",
    "start": 1576571542355,
    "end": 1576571542362,
    "duration": 7,
    "pid": 57457,
    "index": 46
  },
  {
    "name": "Require(39) node_modules/egg/app/extend/helper.js",
    "start": 1576571542362,
    "end": 1576571542362,
    "duration": 0,
    "pid": 57457,
    "index": 47
  },
  {
    "name": "Require(40) app/extend/helper.js",
    "start": 1576571542362,
    "end": 1576571542363,
    "duration": 1,
    "pid": 57457,
    "index": 48
  },
  {
    "name": "Load app.js",
    "start": 1576571542363,
    "end": 1576571542411,
    "duration": 48,
    "pid": 57457,
    "index": 49
  },
  {
    "name": "Require(41) node_modules/egg-session/app.js",
    "start": 1576571542364,
    "end": 1576571542364,
    "duration": 0,
    "pid": 57457,
    "index": 50
  },
  {
    "name": "Require(42) node_modules/egg-security/app.js",
    "start": 1576571542364,
    "end": 1576571542364,
    "duration": 0,
    "pid": 57457,
    "index": 51
  },
  {
    "name": "Require(43) node_modules/egg-onerror/app.js",
    "start": 1576571542365,
    "end": 1576571542368,
    "duration": 3,
    "pid": 57457,
    "index": 52
  },
  {
    "name": "Require(44) node_modules/egg-i18n/app.js",
    "start": 1576571542368,
    "end": 1576571542374,
    "duration": 6,
    "pid": 57457,
    "index": 53
  },
  {
    "name": "Require(45) node_modules/egg-watcher/app.js",
    "start": 1576571542374,
    "end": 1576571542377,
    "duration": 3,
    "pid": 57457,
    "index": 54
  },
  {
    "name": "Require(46) node_modules/egg-schedule/app.js",
    "start": 1576571542377,
    "end": 1576571542378,
    "duration": 1,
    "pid": 57457,
    "index": 55
  },
  {
    "name": "Require(47) node_modules/egg-multipart/app.js",
    "start": 1576571542378,
    "end": 1576571542379,
    "duration": 1,
    "pid": 57457,
    "index": 56
  },
  {
    "name": "Require(48) node_modules/egg-development/app.js",
    "start": 1576571542379,
    "end": 1576571542379,
    "duration": 0,
    "pid": 57457,
    "index": 57
  },
  {
    "name": "Require(49) node_modules/egg-logrotator/app.js",
    "start": 1576571542379,
    "end": 1576571542379,
    "duration": 0,
    "pid": 57457,
    "index": 58
  },
  {
    "name": "Require(50) node_modules/egg-static/app.js",
    "start": 1576571542379,
    "end": 1576571542379,
    "duration": 0,
    "pid": 57457,
    "index": 59
  },
  {
    "name": "Require(51) node_modules/egg-cors/app.js",
    "start": 1576571542380,
    "end": 1576571542380,
    "duration": 0,
    "pid": 57457,
    "index": 60
  },
  {
    "name": "Require(52) node_modules/egg-mysql/app.js",
    "start": 1576571542380,
    "end": 1576571542387,
    "duration": 7,
    "pid": 57457,
    "index": 61
  },
  {
    "name": "Require(53) node_modules/egg-socket.io/app.js",
    "start": 1576571542387,
    "end": 1576571542411,
    "duration": 24,
    "pid": 57457,
    "index": 62
  },
  {
    "name": "Require(54) app.js",
    "start": 1576571542411,
    "end": 1576571542411,
    "duration": 0,
    "pid": 57457,
    "index": 63
  },
  {
    "name": "Before Start in node_modules/egg-watcher/lib/init.js:15:14",
    "start": 1576571542419,
    "end": 1576571542577,
    "duration": 158,
    "pid": 57457,
    "index": 64
  },
  {
    "name": "Before Start in node_modules/egg-mysql/lib/mysql.js:20:7",
    "start": 1576571542488,
    "end": 1576571542617,
    "duration": 129,
    "pid": 57457,
    "index": 65
  },
  {
    "name": "Load Controller",
    "start": 1576571542494,
    "end": 1576571542550,
    "duration": 56,
    "pid": 57457,
    "index": 66
  },
  {
    "name": "Load \"controller\" to Application",
    "start": 1576571542494,
    "end": 1576571542550,
    "duration": 56,
    "pid": 57457,
    "index": 67
  },
  {
    "name": "Before Start in node_modules/egg-socket.io/lib/io.js:26:7",
    "start": 1576571542498,
    "end": 1576571542570,
    "duration": 72,
    "pid": 57457,
    "index": 68
  },
  {
    "name": "Load Service",
    "start": 1576571542498,
    "end": 1576571542502,
    "duration": 4,
    "pid": 57457,
    "index": 69
  },
  {
    "name": "Load \"service\" to Context",
    "start": 1576571542498,
    "end": 1576571542502,
    "duration": 4,
    "pid": 57457,
    "index": 70
  },
  {
    "name": "Load Middleware",
    "start": 1576571542502,
    "end": 1576571542550,
    "duration": 48,
    "pid": 57457,
    "index": 71
  },
  {
    "name": "Load \"middlewares\" to Application",
    "start": 1576571542502,
    "end": 1576571542544,
    "duration": 42,
    "pid": 57457,
    "index": 72
  },
  {
    "name": "Load Controller",
    "start": 1576571542550,
    "end": 1576571542554,
    "duration": 4,
    "pid": 57457,
    "index": 73
  },
  {
    "name": "Load \"controller\" to Application",
    "start": 1576571542550,
    "end": 1576571542554,
    "duration": 4,
    "pid": 57457,
    "index": 74
  },
  {
    "name": "Load Router",
    "start": 1576571542554,
    "end": 1576571542556,
    "duration": 2,
    "pid": 57457,
    "index": 75
  },
  {
    "name": "Require(55) app/router.js",
    "start": 1576571542554,
    "end": 1576571542555,
    "duration": 1,
    "pid": 57457,
    "index": 76
  },
  {
    "name": "Before Start in node_modules/egg-core/lib/egg.js:303:10",
    "start": 1576571542555,
    "end": 1576571542570,
    "duration": 15,
    "pid": 57457,
    "index": 77
  }
]